protarrow/__init__.py
protarrow/arrow_to_proto.py
protarrow/cast_to_proto.py
protarrow/common.py
protarrow/message_extractor.py
protarrow/proto_to_arrow.py
protarrow-0.13.5.dist-info/LICENSE
protarrow-0.13.5.dist-info/METADATA
protarrow-0.13.5.dist-info/NOTICE
protarrow-0.13.5.dist-info/WHEEL
protarrow-0.13.5.dist-info/RECORD
