Metadata-Version: 2.3
Name: protarrow
Version: 0.13.5
Summary: Convert from protobuf to arrow and back
License: Apache-2.0
Keywords: apache-arrow,protobuf,data
Author: Tradewell Tech
Author-email: engineering@tradewelltech.co
Maintainer: 0x26res
Maintainer-email: 0x26res@gmail.com
Requires-Python: >=3.9,<4
Classifier: Development Status :: 4 - Beta
Classifier: License :: OSI Approved :: Apache Software License
Classifier: Natural Language :: English
Classifier: Programming Language :: Python :: 3.9
Classifier: Programming Language :: Python :: 3.10
Classifier: Programming Language :: Python :: 3.11
Classifier: Programming Language :: Python :: 3.12
Classifier: Programming Language :: Python :: 3.13
Requires-Dist: googleapis-common-protos (>=1.53.0)
Requires-Dist: protobuf (>=3.20.1)
Requires-Dist: pyarrow (>=16.0.0)
Project-URL: Bug Tracker, https://github.com/tradewelltech/protarrow/issues
Project-URL: Changelog, https://github.com/tradewelltech/protarrow/blob/main/CHANGELOG.md
